{
  "$schema": "https://json-schema.org/draft/2020-12/schema",
  "$id": "https://raw.githubusercontent.com/MustardSeedNetworks/seed/main/docs/schemas/api/ip-settings-request.schema.json",
  "$ref": "#/$defs/IPSettingsRequest",
  "$defs": {
    "IPSettingsRequest": {
      "properties": {
        "mode": {
          "type": "string"
        },
        "address": {
          "type": "string"
        },
        "netmask": {
          "type": "string"
        },
        "gateway": {
          "type": "string"
        },
        "dns": {
          "items": {
            "type": "string"
          },
          "type": "array"
        }
      },
      "additionalProperties": false,
      "type": "object",
      "required": [
        "mode",
        "address",
        "netmask",
        "gateway",
        "dns"
      ]
    }
  },
  "title": "IPSettingsRequest",
  "description": "IPSettingsRequest — generated from the Go struct in internal/api; refresh with `make schema` after struct changes."
}
